{
  "function_name": "userreg",
  "function_descr": "Registrazione Utente",
  "session": {
    "sess_id": ""
  },
  "data_fields": {
    "fields": [
      {
        "id": "username",
        "label": "LABEL_UTENTE_NOME",
        "mandatory": "true",
        "minlength": 1,
        "maxlength": 50,
        "type": "string"
      },
      {
        "id": "email",
        "label": "LABEL_INDEMAIL",
        "mandatory": "true",
        "minlength": 1,
        "maxlength": 70,
        "type": "string"
      },
      {
        "id": "cognome",
        "label": "LABEL_COGNOME",
        "mandatory": "true",
        "minlength": 1,
        "maxlength": 45,
        "type": "string"
      },
      {
        "id": "nome",
        "label": "LABEL_NOME",
        "mandatory": "true",
        "minlength": 1,
        "maxlength": 45,
        "type": "string"
      },
      {
        "id": "numcell",
        "label": "LABEL_CELLULARE",
        "minlength": 1,
        "maxlength": 20,
        "type": "string"
      },
      {
        "id": "canale",
        "value":"Mob",
        "hidden": true,
        "minlength": 1,
        "maxlength": 1,
        "type": "string"
      },
      {
        "id": "tp_cred",
        "value":"U_P",
        "hidden": true,
        "minlength": 1,
        "maxlength": 3,
        "type": "string"
      }
    ]
  }
}
